{"metadata":{"editor":{"lastEdit":1674035002887}},"timeline":[{"start":9,"end":506,"words":[{"text":"Po- ","start":109,"end":261,"type":0},{"text":"Po- ","start":124,"end":261,"type":0},{"text":"Pop! ","start":153,"end":261,"type":0},{"text":"맛","start":158,"end":406,"type":0},{"text":"테","start":176,"end":406,"type":0},{"text":"탄","start":192,"end":406,"type":0},{"text":"다 ","start":204,"end":406,"type":0},{"text":"맛","start":220,"end":406,"type":0},{"text":"테","start":238,"end":406,"type":0},{"text":"탄","start":252,"end":406,"type":0},{"text":"다 ","start":268,"end":406,"type":0},{"text":"키","start":283,"end":406,"type":0},{"text":"미","start":315,"end":406,"type":0},{"text":"오","start":332,"end":406,"type":0}]},{"start":267,"end":753,"words":[{"text":"Po- ","start":367,"end":511,"type":0},{"text":"Po- ","start":381,"end":511,"type":0},{"text":"Pop! ","start":408,"end":511,"type":0},{"text":"쿄","start":410,"end":653,"type":0},{"text":"오","start":425,"end":653,"type":0},{"text":"와 ","start":439,"end":653,"type":0},{"text":"즛","start":451,"end":653,"type":0},{"text":"토 ","start":465,"end":653,"type":0},{"text":"하","start":497,"end":653,"type":0},{"text":"나","start":510,"end":653,"type":0},{"text":"사","start":525,"end":653,"type":0},{"text":"나","start":539,"end":653,"type":0},{"text":"이","start":571,"end":653,"type":0},{"text":"요","start":585,"end":653,"type":0}]},{"start":518,"end":1042,"words":[{"text":"Po- ","start":618,"end":752,"type":0},{"text":"Po- ","start":632,"end":752,"type":0},{"text":"Pop! ","start":660,"end":752,"type":0},{"text":"Pop","start":661,"end":942,"type":0},{"text":"ping ","start":693,"end":942,"type":0},{"text":"Par","start":725,"end":942,"type":0},{"text":"ty ","start":754,"end":942,"type":0},{"text":"Eve","start":784,"end":942,"type":0},{"text":"ry","start":816,"end":942,"type":0},{"text":"bo","start":833,"end":942,"type":0},{"text":"dy ","start":848,"end":942,"type":0},{"text":"dan","start":877,"end":942,"type":0},{"text":"ce!","start":892,"end":942,"type":0}]},{"start":850,"end":1352,"words":[{"text":"Yeah! ","start":950,"end":1252,"type":3},{"text":"Let's ","start":1037,"end":1252,"type":3},{"text":"gon","start":1077,"end":1252,"type":3},{"text":"na ","start":1098,"end":1252,"type":3},{"text":"par","start":1117,"end":1252,"type":3},{"text":"ty!","start":1142,"end":1252,"type":3}]},{"start":0,"end":100,"words":[{"text":"","start":0,"end":0,"type":0}]},{"start":1099,"end":1716,"words":[{"text":"하","start":1199,"end":1616,"type":3},{"text":"지","start":1224,"end":1616,"type":3},{"text":"케","start":1238,"end":1616,"type":3},{"text":"테 ","start":1257,"end":1616,"type":3},{"text":"Par","start":1322,"end":1616,"type":3},{"text":"ty ","start":1345,"end":1616,"type":3},{"text":"Par","start":1360,"end":1616,"type":3},{"text":"ty ","start":1381,"end":1616,"type":3},{"text":"하","start":1450,"end":1616,"type":3},{"text":"지","start":1473,"end":1616,"type":3},{"text":"케","start":1489,"end":1616,"type":3},{"text":"테?","start":1509,"end":1616,"type":3}]},{"start":1601,"end":2083,"words":[{"text":"하","start":1701,"end":1983,"type":3},{"text":"지","start":1721,"end":1983,"type":3},{"text":"케","start":1737,"end":1983,"type":3},{"text":"테 ","start":1757,"end":1983,"type":3},{"text":"Par","start":1832,"end":1983,"type":3},{"text":"ty ","start":1853,"end":1983,"type":3},{"text":"Par","start":1869,"end":1983,"type":3},{"text":"ty!","start":1888,"end":1983,"type":3}]},{"start":0,"end":100,"words":[{"text":"","start":0,"end":0,"type":0}]},{"start":2361,"end":2985,"words":[{"text":"하","start":2461,"end":2885,"type":0},{"text":"지","start":2491,"end":2885,"type":0},{"text":"메","start":2519,"end":2885,"type":0},{"text":"마","start":2537,"end":2885,"type":0},{"text":"시","start":2581,"end":2885,"type":0},{"text":"테","start":2615,"end":2885,"type":0},{"text":"오 ","start":2647,"end":2885,"type":0},{"text":"난","start":2681,"end":2885,"type":0},{"text":"카","start":2729,"end":2885,"type":0},{"text":"이","start":2745,"end":2885,"type":0},{"text":"데","start":2777,"end":2885,"type":0},{"text":"모","start":2797,"end":2885,"type":0}]},{"start":2797,"end":3373,"words":[{"text":"잇","start":2897,"end":3273,"type":0},{"text":"테 ","start":2926,"end":3273,"type":0},{"text":"미","start":2942,"end":3273,"type":0},{"text":"요","start":2956,"end":3273,"type":0},{"text":"오","start":2970,"end":3273,"type":0},{"text":"카 ","start":2986,"end":3273,"type":0},{"text":"이","start":3062,"end":3273,"type":0},{"text":"츠","start":3078,"end":3273,"type":0},{"text":"모 ","start":3106,"end":3273,"type":0},{"text":"얏","start":3163,"end":3273,"type":0},{"text":"테","start":3182,"end":3273,"type":0},{"text":"루","start":3198,"end":3273,"type":0},{"text":"케","start":3218,"end":3273,"type":0},{"text":"도","start":3245,"end":3273,"type":0}]},{"start":3185,"end":3555,"words":[{"text":"So, ","start":3285,"end":3455,"type":3},{"text":"Pop","start":3317,"end":3455,"type":3},{"text":"ping ","start":3346,"end":3455,"type":3},{"text":"Par","start":3377,"end":3455,"type":3},{"text":"ty!","start":3406,"end":3455,"type":3}]},{"start":3374,"end":4059,"words":[{"text":"신","start":3474,"end":3959,"type":0},{"text":"센","start":3505,"end":3959,"type":0},{"text":"나 ","start":3534,"end":3959,"type":0},{"text":"키","start":3553,"end":3959,"type":0},{"text":"모","start":3597,"end":3959,"type":0},{"text":"치","start":3630,"end":3959,"type":0},{"text":"데","start":3662,"end":3959,"type":0},{"text":"사 ","start":3693,"end":3959,"type":0},{"text":"아","start":3809,"end":3959,"type":0},{"text":"에","start":3824,"end":3959,"type":0},{"text":"루","start":3852,"end":3959,"type":0},{"text":"요","start":3868,"end":3959,"type":0}]},{"start":3881,"end":4547,"words":[{"text":"닷","start":3981,"end":4447,"type":0},{"text":"테 ","start":4006,"end":4447,"type":0},{"text":"콘","start":4074,"end":4447,"type":0},{"text":"야","start":4108,"end":4447,"type":0},{"text":"와 ","start":4124,"end":4447,"type":0},{"text":"모","start":4233,"end":4447,"type":0},{"text":"리","start":4263,"end":4447,"type":0},{"text":"아","start":4291,"end":4447,"type":0},{"text":"갓","start":4324,"end":4447,"type":0},{"text":"테","start":4382,"end":4447,"type":0}]},{"start":4349,"end":4933,"words":[{"text":"이","start":4449,"end":4824,"type":0},{"text":"츠","start":4476,"end":4824,"type":0},{"text":"마","start":4489,"end":4824,"type":0},{"text":"데","start":4508,"end":4824,"type":0},{"text":"모 ","start":4521,"end":4824,"type":0},{"text":"(Hi!) ","start":4551,"end":4584,"type":3},{"text":"이","start":4580,"end":4824,"type":0},{"text":"츠","start":4600,"end":4824,"type":0},{"text":"마","start":4616,"end":4824,"type":0},{"text":"데","start":4633,"end":4824,"type":0},{"text":"모 ","start":4649,"end":4824,"type":0},{"text":"(Hi!) ","start":4678,"end":4699,"type":3},{"text":"오","start":4707,"end":4824,"type":0},{"text":"도","start":4728,"end":4824,"type":0},{"text":"룬","start":4744,"end":4824,"type":0},{"text":"다","start":4760,"end":4824,"type":0},{"text":"몬 ","start":4776,"end":4824,"type":0},{"text":"(Hi!)","start":4804,"end":4833,"type":3}]},{"start":4733,"end":5103,"words":[{"text":"못","start":4833,"end":5003,"type":3},{"text":"토 ","start":4855,"end":5003,"type":3},{"text":"못","start":4867,"end":5003,"type":3},{"text":"토 ","start":4886,"end":5003,"type":3},{"text":"못","start":4899,"end":5003,"type":3},{"text":"토 ","start":4920,"end":5003,"type":3},{"text":"못","start":4933,"end":5003,"type":3},{"text":"토?","start":4945,"end":5003,"type":3}]},{"start":4858,"end":5432,"words":[{"text":"이","start":4958,"end":5332,"type":0},{"text":"츠","start":4984,"end":5332,"type":0},{"text":"마","start":4999,"end":5332,"type":0},{"text":"데","start":5016,"end":5332,"type":0},{"text":"모 ","start":5028,"end":5332,"type":0},{"text":"(Hi!) ","start":5058,"end":5083,"type":3},{"text":"이","start":5088,"end":5332,"type":0},{"text":"츠","start":5105,"end":5332,"type":0},{"text":"마","start":5122,"end":5332,"type":0},{"text":"데","start":5139,"end":5332,"type":0},{"text":"모 ","start":5153,"end":5332,"type":0},{"text":"(Hi!) ","start":5182,"end":5208,"type":3},{"text":"오","start":5211,"end":5332,"type":0},{"text":"도","start":5233,"end":5332,"type":0},{"text":"룬","start":5249,"end":5332,"type":0},{"text":"다","start":5267,"end":5332,"type":0},{"text":"몬 ","start":5282,"end":5332,"type":0},{"text":"(Hi!)","start":5308,"end":5332,"type":3}]},{"start":5234,"end":5624,"words":[{"text":"Wo","start":5334,"end":5524,"type":3},{"text":"o.. ","start":5353,"end":5524,"type":3},{"text":"O","start":5398,"end":5524,"type":3},{"text":"K!","start":5415,"end":5524,"type":3}]},{"start":0,"end":100,"words":[{"text":"","start":0,"end":0,"type":0}]},{"start":5399,"end":6091,"words":[{"text":"콘","start":5499,"end":5991,"type":0},{"text":"나","start":5527,"end":5991,"type":0},{"text":"니 ","start":5555,"end":5991,"type":0},{"text":"나","start":5576,"end":5991,"type":0},{"text":"카","start":5618,"end":5991,"type":0},{"text":"요","start":5650,"end":5991,"type":0},{"text":"쿠 ","start":5679,"end":5991,"type":0},{"text":"나","start":5751,"end":5991,"type":0},{"text":"레","start":5782,"end":5991,"type":0},{"text":"루","start":5809,"end":5991,"type":0},{"text":"난","start":5832,"end":5991,"type":0},{"text":"테","start":5903,"end":5991,"type":0},{"text":"네","start":5932,"end":5991,"type":0}]},{"start":5900,"end":6585,"words":[{"text":"후","start":6000,"end":6485,"type":0},{"text":"시","start":6017,"end":6485,"type":0},{"text":"기","start":6032,"end":6485,"type":0},{"text":"난","start":6061,"end":6485,"type":0},{"text":"다 ","start":6094,"end":6485,"type":0},{"text":"이","start":6126,"end":6485,"type":0},{"text":"마","start":6158,"end":6485,"type":0},{"text":"데","start":6186,"end":6485,"type":0},{"text":"모 ","start":6218,"end":6485,"type":0},{"text":"Ah! ","start":6309,"end":6485,"type":3},{"text":"이","start":6342,"end":6485,"type":3},{"text":"이","start":6357,"end":6485,"type":3},{"text":"키","start":6381,"end":6485,"type":3},{"text":"분!","start":6397,"end":6485,"type":3}]},{"start":6406,"end":7074,"words":[{"text":"우","start":6506,"end":6974,"type":0},{"text":"레","start":6522,"end":6974,"type":0},{"text":"시","start":6538,"end":6974,"type":0},{"text":"이 ","start":6550,"end":6974,"type":0},{"text":"토","start":6570,"end":6974,"type":0},{"text":"키","start":6589,"end":6974,"type":0},{"text":"와 ","start":6602,"end":6974,"type":0},{"text":"잇","start":6631,"end":6974,"type":0},{"text":"쇼","start":6666,"end":6974,"type":0},{"text":"니 ","start":6697,"end":6974,"type":0},{"text":"오","start":6754,"end":6974,"type":0},{"text":"도","start":6778,"end":6974,"type":0},{"text":"리","start":6801,"end":6974,"type":0},{"text":"아","start":6821,"end":6974,"type":0},{"text":"카","start":6841,"end":6974,"type":0},{"text":"소","start":6861,"end":6974,"type":0},{"text":"오","start":6875,"end":6974,"type":0},{"text":"요","start":6910,"end":6974,"type":0}]},{"start":6871,"end":7357,"words":[{"text":"톤","start":6971,"end":7194,"type":0},{"text":"다","start":6990,"end":7194,"type":0},{"text":"라..! ","start":7003,"end":7194,"type":0},{"text":"(민","start":7035,"end":7124,"type":3},{"text":"나","start":7052,"end":7124,"type":3},{"text":"데?) ","start":7066,"end":7124,"type":3},{"text":"톤","start":7101,"end":7194,"type":0},{"text":"다","start":7120,"end":7194,"type":0},{"text":"라! ","start":7135,"end":7194,"type":0},{"text":"(민","start":7162,"end":7257,"type":3},{"text":"나","start":7180,"end":7257,"type":3},{"text":"데!)","start":7196,"end":7257,"type":3}]},{"start":7130,"end":7589,"words":[{"text":"톤","start":7230,"end":7489,"type":0},{"text":"다","start":7247,"end":7489,"type":0},{"text":"라 ","start":7262,"end":7489,"type":0},{"text":"와","start":7298,"end":7489,"type":0},{"text":"카","start":7319,"end":7489,"type":0},{"text":"룬","start":7334,"end":7489,"type":0},{"text":"다!","start":7362,"end":7489,"type":0}]},{"start":0,"end":100,"words":[{"text":"","start":0,"end":0,"type":0}]},{"start":7417,"end":8244,"words":[{"text":"타","start":7517,"end":8144,"type":0},{"text":"노","start":7544,"end":8144,"type":0},{"text":"시","start":7573,"end":8144,"type":0},{"text":"쿠","start":7603,"end":8144,"type":0},{"text":"테 ","start":7638,"end":8144,"type":0},{"text":"이","start":7705,"end":8144,"type":0},{"text":"치","start":7735,"end":8144,"type":0},{"text":"니","start":7764,"end":8144,"type":0},{"text":"치","start":7793,"end":8144,"type":0},{"text":"가 ","start":7824,"end":8144,"type":0},{"text":"미","start":7854,"end":8144,"type":0},{"text":"지","start":7904,"end":8144,"type":0},{"text":"카","start":7947,"end":8144,"type":0},{"text":"이","start":7979,"end":8144,"type":0},{"text":"카","start":8062,"end":8144,"type":0},{"text":"라","start":8076,"end":8144,"type":0},{"text":"네","start":8100,"end":8144,"type":0}]},{"start":8047,"end":8738,"words":[{"text":"오","start":8147,"end":8638,"type":0},{"text":"모","start":8177,"end":8638,"type":0},{"text":"잇","start":8206,"end":8638,"type":0},{"text":"키","start":8235,"end":8638,"type":0},{"text":"리 ","start":8265,"end":8638,"type":0},{"text":"와","start":8330,"end":8638,"type":0},{"text":"라","start":8350,"end":8638,"type":0},{"text":"이","start":8363,"end":8638,"type":0},{"text":"나","start":8421,"end":8638,"type":0},{"text":"가","start":8485,"end":8638,"type":0},{"text":"라","start":8542,"end":8638,"type":0}]},{"start":8549,"end":9249,"words":[{"text":"아","start":8649,"end":9149,"type":0},{"text":"시","start":8677,"end":9149,"type":0},{"text":"타","start":8709,"end":9149,"type":0},{"text":"노 ","start":8725,"end":9149,"type":0},{"text":"코","start":8778,"end":9149,"type":0},{"text":"토","start":8807,"end":9149,"type":0},{"text":"와 ","start":8837,"end":9149,"type":0},{"text":"아","start":8906,"end":9149,"type":0},{"text":"시","start":8935,"end":9149,"type":0},{"text":"타 ","start":8963,"end":9149,"type":0},{"text":"칸","start":8982,"end":9149,"type":0},{"text":"가","start":9026,"end":9149,"type":0},{"text":"에","start":9058,"end":9149,"type":0},{"text":"요","start":9090,"end":9149,"type":0},{"text":"오","start":9106,"end":9149,"type":0}]},{"start":9054,"end":10134,"words":[{"text":"유","start":9154,"end":10034,"type":0},{"text":"메","start":9185,"end":10034,"type":0},{"text":"노 ","start":9207,"end":10034,"type":0},{"text":"요","start":9227,"end":10034,"type":0},{"text":"오","start":9246,"end":10034,"type":0},{"text":"나 ","start":9295,"end":10034,"type":0},{"text":"슌","start":9467,"end":10034,"type":0},{"text":"칸","start":9499,"end":10034,"type":0},{"text":"가 ","start":9559,"end":10034,"type":0},{"text":"코","start":9594,"end":10034,"type":0},{"text":"코","start":9614,"end":10034,"type":0},{"text":"니 ","start":9630,"end":10034,"type":0},{"text":"아","start":9681,"end":10034,"type":0},{"text":"루","start":9723,"end":10034,"type":0},{"text":"요","start":9742,"end":10034,"type":0}]},{"start":0,"end":100,"words":[{"text":"","start":0,"end":0,"type":0}]},{"start":10062,"end":10648,"words":[{"text":"하","start":10162,"end":10548,"type":3},{"text":"지","start":10186,"end":10548,"type":3},{"text":"케","start":10201,"end":10548,"type":3},{"text":"테 ","start":10218,"end":10548,"type":3},{"text":"Par","start":10289,"end":10548,"type":3},{"text":"ty ","start":10309,"end":10548,"type":3},{"text":"Par","start":10326,"end":10548,"type":3},{"text":"ty ","start":10345,"end":10548,"type":3},{"text":"하","start":10416,"end":10548,"type":3},{"text":"지","start":10438,"end":10548,"type":3},{"text":"케","start":10454,"end":10548,"type":3},{"text":"테?","start":10473,"end":10548,"type":3}]},{"start":10573,"end":11106,"words":[{"text":"하","start":10673,"end":11006,"type":3},{"text":"지","start":10693,"end":11006,"type":3},{"text":"케","start":10709,"end":11006,"type":3},{"text":"테 ","start":10725,"end":11006,"type":3},{"text":"Par","start":10798,"end":11006,"type":3},{"text":"ty ","start":10818,"end":11006,"type":3},{"text":"Par","start":10833,"end":11006,"type":3},{"text":"ty!","start":10853,"end":11006,"type":3}]},{"start":0,"end":100,"words":[{"text":"","start":0,"end":0,"type":0}]},{"start":11333,"end":11959,"words":[{"text":"히","start":11433,"end":11859,"type":0},{"text":"토","start":11460,"end":11859,"type":0},{"text":"미","start":11487,"end":11859,"type":0},{"text":"시","start":11507,"end":11859,"type":0},{"text":"리","start":11547,"end":11859,"type":0},{"text":"데","start":11580,"end":11859,"type":0},{"text":"모 ","start":11613,"end":11859,"type":0},{"text":"다","start":11645,"end":11859,"type":0},{"text":"이","start":11679,"end":11859,"type":0},{"text":"죠","start":11699,"end":11859,"type":0},{"text":"오","start":11731,"end":11859,"type":0},{"text":"부","start":11749,"end":11859,"type":0},{"text":"사","start":11764,"end":11859,"type":0}]},{"start":11767,"end":12349,"words":[{"text":"오","start":11867,"end":12249,"type":0},{"text":"나","start":11888,"end":12249,"type":0},{"text":"지","start":11906,"end":12249,"type":0},{"text":"다","start":11919,"end":12249,"type":0},{"text":"요 ","start":11951,"end":12249,"type":0},{"text":"지","start":12018,"end":12249,"type":0},{"text":"츠","start":12038,"end":12249,"type":0},{"text":"와 ","start":12073,"end":12249,"type":0},{"text":"카","start":12126,"end":12249,"type":0},{"text":"나","start":12144,"end":12249,"type":0},{"text":"리 ","start":12160,"end":12249,"type":0},{"text":"Shy ","start":12178,"end":12249,"type":0},{"text":"Heart!","start":12210,"end":12249,"type":0}]},{"start":12154,"end":12564,"words":[{"text":"So, ","start":12254,"end":12464,"type":3},{"text":"too ","start":12285,"end":12464,"type":3},{"text":"shy ","start":12317,"end":12464,"type":3},{"text":"my ","start":12350,"end":12464,"type":3},{"text":"heart!","start":12380,"end":12464,"type":3}]},{"start":12345,"end":13026,"words":[{"text":"손","start":12445,"end":12926,"type":0},{"text":"나","start":12474,"end":12926,"type":0},{"text":"노 ","start":12502,"end":12926,"type":0},{"text":"와","start":12526,"end":12926,"type":0},{"text":"스","start":12563,"end":12926,"type":0},{"text":"레","start":12598,"end":12926,"type":0},{"text":"챠","start":12633,"end":12926,"type":0},{"text":"우 ","start":12664,"end":12926,"type":0},{"text":"쿠","start":12772,"end":12926,"type":0},{"text":"라","start":12790,"end":12926,"type":0},{"text":"이","start":12819,"end":12926,"type":0},{"text":"니","start":12835,"end":12926,"type":0}]},{"start":12844,"end":13511,"words":[{"text":"즛","start":12944,"end":13411,"type":0},{"text":"토 ","start":12975,"end":13411,"type":0},{"text":"콘","start":13033,"end":13411,"type":0},{"text":"야","start":13067,"end":13411,"type":0},{"text":"와 ","start":13083,"end":13411,"type":0},{"text":"사","start":13194,"end":13411,"type":0},{"text":"와","start":13226,"end":13411,"type":0},{"text":"기","start":13252,"end":13411,"type":0},{"text":"타","start":13282,"end":13411,"type":0},{"text":"이","start":13321,"end":13411,"type":0},{"text":"나","start":13341,"end":13411,"type":0}]},{"start":0,"end":100,"words":[{"text":"","start":0,"end":0,"type":0}]},{"start":13320,"end":13892,"words":[{"text":"이","start":13420,"end":13792,"type":0},{"text":"츠","start":13444,"end":13792,"type":0},{"text":"마","start":13459,"end":13792,"type":0},{"text":"데","start":13475,"end":13792,"type":0},{"text":"모 ","start":13486,"end":13792,"type":0},{"text":"(Hi!) ","start":13513,"end":13539,"type":3},{"text":"이","start":13544,"end":13792,"type":0},{"text":"츠","start":13565,"end":13792,"type":0},{"text":"마","start":13583,"end":13792,"type":0},{"text":"데","start":13596,"end":13792,"type":0},{"text":"모 ","start":13608,"end":13792,"type":0},{"text":"(Hi!) ","start":13643,"end":13666,"type":3},{"text":"오","start":13674,"end":13792,"type":0},{"text":"도","start":13697,"end":13792,"type":0},{"text":"룬","start":13712,"end":13792,"type":0},{"text":"다","start":13729,"end":13792,"type":0},{"text":"몬! ","start":13743,"end":13792,"type":0},{"text":"(Hi!)","start":13769,"end":13792,"type":3}]},{"start":13705,"end":14064,"words":[{"text":"못","start":13805,"end":13964,"type":3},{"text":"토 ","start":13825,"end":13964,"type":3},{"text":"못","start":13837,"end":13964,"type":3},{"text":"토 ","start":13860,"end":13964,"type":3},{"text":"못","start":13869,"end":13964,"type":3},{"text":"토 ","start":13888,"end":13964,"type":3},{"text":"못","start":13901,"end":13964,"type":3},{"text":"토?","start":13914,"end":13964,"type":3}]},{"start":13828,"end":14401,"words":[{"text":"이","start":13928,"end":14309,"type":0},{"text":"츠","start":13950,"end":14309,"type":0},{"text":"마","start":13964,"end":14309,"type":0},{"text":"데","start":13980,"end":14309,"type":0},{"text":"모 ","start":13996,"end":14309,"type":0},{"text":"(Hi!) ","start":14023,"end":14052,"type":3},{"text":"이","start":14051,"end":14309,"type":0},{"text":"츠","start":14071,"end":14309,"type":0},{"text":"마","start":14087,"end":14309,"type":0},{"text":"데","start":14103,"end":14309,"type":0},{"text":"모 ","start":14118,"end":14309,"type":0},{"text":"(Hi!) ","start":14143,"end":14176,"type":3},{"text":"오","start":14176,"end":14309,"type":0},{"text":"도","start":14198,"end":14309,"type":0},{"text":"룬","start":14212,"end":14309,"type":0},{"text":"다","start":14231,"end":14309,"type":0},{"text":"몬! ","start":14244,"end":14309,"type":0},{"text":"(Hi!)","start":14271,"end":14301,"type":3}]},{"start":14204,"end":14572,"words":[{"text":"Wo","start":14304,"end":14472,"type":3},{"text":"o.. ","start":14321,"end":14472,"type":3},{"text":"O","start":14376,"end":14472,"type":3},{"text":"K!","start":14392,"end":14472,"type":3}]},{"start":0,"end":100,"words":[{"text":"","start":0,"end":0,"type":0}]},{"start":14369,"end":15067,"words":[{"text":"에","start":14469,"end":14967,"type":0},{"text":"가","start":14489,"end":14967,"type":0},{"text":"옷","start":14503,"end":14967,"type":0},{"text":"테 ","start":14525,"end":14967,"type":0},{"text":"우","start":14542,"end":14967,"type":0},{"text":"츠","start":14584,"end":14967,"type":0},{"text":"룬","start":14613,"end":14967,"type":0},{"text":"다 ","start":14645,"end":14967,"type":0},{"text":"이","start":14713,"end":14967,"type":0},{"text":"츠","start":14738,"end":14967,"type":0},{"text":"노 ","start":14772,"end":14967,"type":0},{"text":"마","start":14790,"end":14967,"type":0},{"text":"니","start":14833,"end":14967,"type":0},{"text":"카","start":14869,"end":14967,"type":0},{"text":"사","start":14899,"end":14967,"type":0}]},{"start":14867,"end":15560,"words":[{"text":"오","start":14967,"end":15460,"type":0},{"text":"오","start":14984,"end":15460,"type":0},{"text":"키","start":14998,"end":15460,"type":0},{"text":"이 ","start":15011,"end":15460,"type":0},{"text":"코","start":15031,"end":15460,"type":0},{"text":"에","start":15047,"end":15460,"type":0},{"text":"데 ","start":15060,"end":15460,"type":0},{"text":"사","start":15095,"end":15460,"type":0},{"text":"켄","start":15124,"end":15460,"type":0},{"text":"데","start":15156,"end":15460,"type":0},{"text":"타 ","start":15187,"end":15460,"type":0},{"text":"Ah! ","start":15282,"end":15460,"type":3},{"text":"이","start":15313,"end":15460,"type":3},{"text":"이","start":15330,"end":15460,"type":3},{"text":"키","start":15346,"end":15460,"type":3},{"text":"분!","start":15364,"end":15460,"type":3}]},{"start":15371,"end":16045,"words":[{"text":"사","start":15471,"end":15945,"type":0},{"text":"미","start":15487,"end":15945,"type":0},{"text":"시","start":15503,"end":15945,"type":0},{"text":"이 ","start":15516,"end":15945,"type":0},{"text":"토","start":15543,"end":15945,"type":0},{"text":"키","start":15559,"end":15945,"type":0},{"text":"와 ","start":15573,"end":15945,"type":0},{"text":"오","start":15601,"end":15945,"type":0},{"text":"이","start":15616,"end":15945,"type":0},{"text":"데","start":15631,"end":15945,"type":0},{"text":"요 ","start":15662,"end":15945,"type":0},{"text":"오","start":15724,"end":15945,"type":0},{"text":"도","start":15745,"end":15945,"type":0},{"text":"리 ","start":15762,"end":15945,"type":0},{"text":"아","start":15780,"end":15945,"type":0},{"text":"카","start":15800,"end":15945,"type":0},{"text":"소","start":15817,"end":15945,"type":0},{"text":"오","start":15835,"end":15945,"type":0},{"text":"요","start":15885,"end":15945,"type":0}]},{"start":15842,"end":16305,"words":[{"text":"톤","start":15942,"end":16174,"type":0},{"text":"다","start":15960,"end":16174,"type":0},{"text":"라..! ","start":15974,"end":16174,"type":0},{"text":"(민","start":16004,"end":16095,"type":3},{"text":"나","start":16023,"end":16095,"type":3},{"text":"데?) ","start":16039,"end":16095,"type":3},{"text":"톤","start":16074,"end":16174,"type":0},{"text":"다","start":16090,"end":16174,"type":0},{"text":"라! ","start":16106,"end":16174,"type":0},{"text":"(민","start":16131,"end":16205,"type":3},{"text":"나","start":16148,"end":16205,"type":3},{"text":"데!)","start":16164,"end":16205,"type":3}]},{"start":16097,"end":16567,"words":[{"text":"톤","start":16197,"end":16467,"type":0},{"text":"다","start":16213,"end":16467,"type":0},{"text":"라 ","start":16230,"end":16467,"type":0},{"text":"와","start":16260,"end":16467,"type":0},{"text":"카","start":16277,"end":16467,"type":0},{"text":"룬","start":16293,"end":16467,"type":0},{"text":"다!","start":16326,"end":16467,"type":0}]},{"start":0,"end":100,"words":[{"text":"","start":0,"end":0,"type":0}]},{"start":16387,"end":17216,"words":[{"text":"오","start":16487,"end":17116,"type":0},{"text":"모","start":16515,"end":17116,"type":0},{"text":"시","start":16542,"end":17116,"type":0},{"text":"로","start":16569,"end":17116,"type":0},{"text":"쿠 ","start":16602,"end":17116,"type":0},{"text":"스","start":16669,"end":17116,"type":0},{"text":"고","start":16697,"end":17116,"type":0},{"text":"시","start":16733,"end":17116,"type":0},{"text":"타","start":16763,"end":17116,"type":0},{"text":"이 ","start":16793,"end":17116,"type":0},{"text":"소","start":16826,"end":17116,"type":0},{"text":"레","start":16874,"end":17116,"type":0},{"text":"다","start":16917,"end":17116,"type":0},{"text":"케","start":16950,"end":17116,"type":0},{"text":"다","start":17031,"end":17116,"type":0},{"text":"요","start":17048,"end":17116,"type":0},{"text":"네","start":17070,"end":17116,"type":0}]},{"start":17020,"end":17702,"words":[{"text":"유","start":17120,"end":17602,"type":0},{"text":"우","start":17137,"end":17602,"type":0},{"text":"우","start":17151,"end":17602,"type":0},{"text":"츠","start":17179,"end":17602,"type":0},{"text":"난","start":17207,"end":17602,"type":0},{"text":"테 ","start":17235,"end":17602,"type":0},{"text":"오","start":17300,"end":17602,"type":0},{"text":"도","start":17319,"end":17602,"type":0},{"text":"리 ","start":17335,"end":17602,"type":0},{"text":"토","start":17392,"end":17602,"type":0},{"text":"바","start":17448,"end":17602,"type":0},{"text":"소","start":17495,"end":17602,"type":0},{"text":"오","start":17529,"end":17602,"type":0}]},{"start":17516,"end":18289,"words":[{"text":"나","start":17616,"end":18189,"type":0},{"text":"야","start":17644,"end":18189,"type":0},{"text":"미","start":17674,"end":18189,"type":0},{"text":"가 ","start":17696,"end":18189,"type":0},{"text":"아","start":17738,"end":18189,"type":0},{"text":"세","start":17773,"end":18189,"type":0},{"text":"데 ","start":17804,"end":18189,"type":0},{"text":"나","start":17872,"end":18189,"type":0},{"text":"가","start":17896,"end":18189,"type":0},{"text":"레","start":17930,"end":18189,"type":0},{"text":"테 ","start":17948,"end":18189,"type":0},{"text":"키","start":17997,"end":18189,"type":0},{"text":"에","start":18029,"end":18189,"type":0},{"text":"테","start":18058,"end":18189,"type":0}]},{"start":18087,"end":18605,"words":[{"text":"카","start":18187,"end":18505,"type":0},{"text":"라","start":18204,"end":18505,"type":0},{"text":"다 ","start":18220,"end":18505,"type":0},{"text":"카","start":18250,"end":18505,"type":0},{"text":"루","start":18269,"end":18505,"type":0},{"text":"이 ","start":18289,"end":18505,"type":0},{"text":"미","start":18353,"end":18505,"type":0},{"text":"타","start":18373,"end":18505,"type":0},{"text":"이","start":18388,"end":18505,"type":0},{"text":"사","start":18401,"end":18505,"type":0}]},{"start":18407,"end":19239,"words":[{"text":"타","start":18507,"end":19139,"type":0},{"text":"노","start":18536,"end":19139,"type":0},{"text":"시","start":18564,"end":19139,"type":0},{"text":"이 ","start":18580,"end":19139,"type":0},{"text":"히","start":18605,"end":19139,"type":0},{"text":"와 ","start":18635,"end":19139,"type":0},{"text":"앗","start":18697,"end":19139,"type":0},{"text":"토 ","start":18723,"end":19139,"type":0},{"text":"이","start":18750,"end":19139,"type":0},{"text":"우","start":18769,"end":19139,"type":0},{"text":"마","start":18784,"end":19139,"type":0},{"text":"니 ","start":18813,"end":19139,"type":0},{"text":"오","start":18850,"end":19139,"type":0},{"text":"와","start":18894,"end":19139,"type":0},{"text":"룻","start":18936,"end":19139,"type":0},{"text":"테 ","start":18971,"end":19139,"type":0},{"text":"코","start":19052,"end":19139,"type":0},{"text":"토","start":19068,"end":19139,"type":0},{"text":"오","start":19091,"end":19139,"type":0}]},{"start":19040,"end":19729,"words":[{"text":"이","start":19140,"end":19629,"type":0},{"text":"마","start":19169,"end":19629,"type":0},{"text":"와 ","start":19194,"end":19629,"type":0},{"text":"마","start":19225,"end":19629,"type":0},{"text":"다 ","start":19257,"end":19629,"type":0},{"text":"이","start":19318,"end":19629,"type":0},{"text":"와","start":19336,"end":19629,"type":0},{"text":"나","start":19353,"end":19629,"type":0},{"text":"이","start":19365,"end":19629,"type":0},{"text":"데 ","start":19416,"end":19629,"type":0},{"text":"이","start":19477,"end":19629,"type":0},{"text":"테","start":19528,"end":19629,"type":0}]},{"start":19544,"end":20246,"words":[{"text":"카","start":19644,"end":20146,"type":0},{"text":"에","start":19672,"end":20146,"type":0},{"text":"리","start":19703,"end":20146,"type":0},{"text":"타","start":19720,"end":20146,"type":0},{"text":"쿠","start":19763,"end":20146,"type":0},{"text":"나","start":19796,"end":20146,"type":0},{"text":"이 ","start":19827,"end":20146,"type":0},{"text":"카","start":19895,"end":20146,"type":0},{"text":"에","start":19923,"end":20146,"type":0},{"text":"라","start":19953,"end":20146,"type":0},{"text":"나","start":19972,"end":20146,"type":0},{"text":"이","start":19986,"end":20146,"type":0},{"text":"데 ","start":20024,"end":20146,"type":0},{"text":"이","start":20053,"end":20146,"type":0},{"text":"이","start":20072,"end":20146,"type":0},{"text":"요","start":20086,"end":20146,"type":0}]},{"start":20041,"end":21101,"words":[{"text":"유","start":20141,"end":21001,"type":0},{"text":"메","start":20173,"end":21001,"type":0},{"text":"노 ","start":20200,"end":21001,"type":0},{"text":"요","start":20225,"end":21001,"type":0},{"text":"오","start":20243,"end":21001,"type":0},{"text":"나 ","start":20285,"end":21001,"type":0},{"text":"슌","start":20461,"end":21001,"type":0},{"text":"칸","start":20488,"end":21001,"type":0},{"text":"가 ","start":20548,"end":21001,"type":0},{"text":"코","start":20583,"end":21001,"type":0},{"text":"코","start":20607,"end":21001,"type":0},{"text":"니 ","start":20623,"end":21001,"type":0},{"text":"아","start":20667,"end":21001,"type":0},{"text":"루","start":20707,"end":21001,"type":0},{"text":"요","start":20726,"end":21001,"type":0}]},{"start":0,"end":100,"words":[{"text":"","start":0,"end":0,"type":0}]},{"start":20979,"end":21474,"words":[{"text":"Po- ","start":21079,"end":21215,"type":0},{"text":"Po- ","start":21093,"end":21215,"type":0},{"text":"Pop! ","start":21120,"end":21215,"type":0},{"text":"이","start":21122,"end":21537,"type":0},{"text":"츠","start":21142,"end":21537,"type":0},{"text":"마","start":21160,"end":21537,"type":0},{"text":"데","start":21176,"end":21537,"type":0},{"text":"모 ","start":21190,"end":21537,"type":0},{"text":"(Hi!) ","start":21219,"end":21263,"type":3},{"text":"이","start":21257,"end":21537,"type":0},{"text":"츠","start":21276,"end":21537,"type":0},{"text":"마","start":21290,"end":21537,"type":0},{"text":"데","start":21309,"end":21537,"type":0},{"text":"모 ","start":21321,"end":21537,"type":0},{"text":"(Hi!)","start":21341,"end":21374,"type":3}]},{"start":21281,"end":21632,"words":[{"text":"오","start":21381,"end":21537,"type":0},{"text":"도","start":21398,"end":21537,"type":0},{"text":"룬","start":21413,"end":21537,"type":0},{"text":"다","start":21429,"end":21537,"type":0},{"text":"몬! ","start":21445,"end":21537,"type":0},{"text":"(Hi!)","start":21468,"end":21532,"type":3}]},{"start":21488,"end":21979,"words":[{"text":"Po- ","start":21588,"end":21690,"type":0},{"text":"Po- ","start":21602,"end":21690,"type":0},{"text":"Pop! ","start":21630,"end":21690,"type":0},{"text":"이","start":21629,"end":21877,"type":0},{"text":"츠","start":21649,"end":21877,"type":0},{"text":"마","start":21666,"end":21877,"type":0},{"text":"데","start":21684,"end":21877,"type":0},{"text":"모 ","start":21698,"end":21877,"type":0},{"text":"(Hi!) ","start":21722,"end":21765,"type":3},{"text":"오","start":21759,"end":21877,"type":0},{"text":"도","start":21779,"end":21877,"type":0},{"text":"룬","start":21796,"end":21877,"type":0},{"text":"다","start":21811,"end":21877,"type":0},{"text":"몬! ","start":21825,"end":21877,"type":0},{"text":"(Hi!)","start":21850,"end":21879,"type":3}]},{"start":21781,"end":22241,"words":[{"text":"민","start":21881,"end":22141,"type":0},{"text":"나","start":21905,"end":22141,"type":0},{"text":"데 ","start":21921,"end":22141,"type":0},{"text":"민","start":21935,"end":22141,"type":0},{"text":"나","start":21966,"end":22141,"type":0},{"text":"데 ","start":21983,"end":22141,"type":0},{"text":"오","start":22005,"end":22141,"type":0},{"text":"도","start":22037,"end":22141,"type":0},{"text":"리","start":22053,"end":22141,"type":0},{"text":"타","start":22070,"end":22141,"type":0},{"text":"이","start":22098,"end":22141,"type":0}]},{"start":0,"end":100,"words":[{"text":"","start":0,"end":0,"type":0}]},{"start":21997,"end":22301,"words":[{"text":"Po- ","start":22097,"end":22201,"type":0},{"text":"Po- ","start":22110,"end":22201,"type":0},{"text":"Pop!","start":22140,"end":22201,"type":0}]},{"start":22037,"end":22508,"words":[{"text":"톤","start":22137,"end":22394,"type":0},{"text":"데","start":22152,"end":22394,"type":0},{"text":"미","start":22165,"end":22394,"type":0},{"text":"루","start":22177,"end":22394,"type":0},{"text":"요 ","start":22189,"end":22394,"type":0},{"text":"톤","start":22203,"end":22394,"type":0},{"text":"데","start":22215,"end":22394,"type":0},{"text":"미","start":22228,"end":22394,"type":0},{"text":"루","start":22240,"end":22394,"type":0},{"text":"요 ","start":22252,"end":22394,"type":0},{"text":"못","start":22264,"end":22394,"type":0},{"text":"토 ","start":22303,"end":22394,"type":0},{"text":"(Pop","start":22281,"end":22408,"type":3},{"text":"ping ","start":22312,"end":22408,"type":3},{"text":"Jump!)","start":22350,"end":22408,"type":3}]},{"start":22286,"end":22755,"words":[{"text":"민","start":22386,"end":22655,"type":0},{"text":"나 ","start":22413,"end":22655,"type":0},{"text":"민","start":22426,"end":22655,"type":0},{"text":"나 ","start":22449,"end":22655,"type":0},{"text":"츠","start":22462,"end":22655,"type":0},{"text":"이","start":22474,"end":22655,"type":0},{"text":"테 ","start":22486,"end":22655,"type":0},{"text":"키","start":22498,"end":22655,"type":0},{"text":"테 ","start":22510,"end":22655,"type":0},{"text":"잇","start":22522,"end":22655,"type":0},{"text":"쇼","start":22550,"end":22655,"type":0},{"text":"니!","start":22566,"end":22655,"type":0}]},{"start":22497,"end":22940,"words":[{"text":"Par","start":22597,"end":23006,"type":0},{"text":"ty ","start":22613,"end":23006,"type":0},{"text":"night, ","start":22643,"end":23006,"type":0},{"text":"(Hi!) ","start":22667,"end":22712,"type":3},{"text":"Par","start":22726,"end":23006,"type":0},{"text":"ty ","start":22742,"end":23006,"type":0},{"text":"night, ","start":22774,"end":23006,"type":0},{"text":"(Hi!)","start":22795,"end":22840,"type":3}]},{"start":22756,"end":23106,"words":[{"text":"Par","start":22856,"end":23006,"type":0},{"text":"ty ","start":22871,"end":23006,"type":0},{"text":"night ","start":22901,"end":23006,"type":0},{"text":"(Come ","start":22933,"end":23006,"type":3},{"text":"on!)","start":22949,"end":23006,"type":3}]},{"start":22917,"end":23399,"words":[{"text":"Yeah!","start":23017,"end":23299,"type":3}]},{"start":0,"end":100,"words":[{"text":"","start":0,"end":0,"type":0}]},{"start":22988,"end":25610,"words":[{"text":"< 간주 부분 : ","start":23088,"end":25510,"type":2},{"text":"하이 ","start":23176,"end":25510,"type":1},{"text":"x (간주 끝까지) ","start":23176,"end":25510,"type":2},{"text":">","start":23088,"end":25510,"type":2}]},{"start":0,"end":100,"words":[{"text":"","start":0,"end":0,"type":0}]},{"start":25478,"end":26304,"words":[{"text":"오","start":25578,"end":26204,"type":0},{"text":"모","start":25608,"end":26204,"type":0},{"text":"시","start":25640,"end":26204,"type":0},{"text":"로","start":25671,"end":26204,"type":0},{"text":"쿠 ","start":25700,"end":26204,"type":0},{"text":"스","start":25763,"end":26204,"type":0},{"text":"고","start":25796,"end":26204,"type":0},{"text":"시","start":25827,"end":26204,"type":0},{"text":"타","start":25856,"end":26204,"type":0},{"text":"이 ","start":25888,"end":26204,"type":0},{"text":"소","start":25921,"end":26204,"type":0},{"text":"레","start":25970,"end":26204,"type":0},{"text":"다","start":26012,"end":26204,"type":0},{"text":"케","start":26048,"end":26204,"type":0},{"text":"다","start":26125,"end":26204,"type":0},{"text":"요","start":26140,"end":26204,"type":0},{"text":"네","start":26168,"end":26204,"type":0}]},{"start":26107,"end":26797,"words":[{"text":"유","start":26207,"end":26697,"type":0},{"text":"우","start":26224,"end":26697,"type":0},{"text":"우","start":26240,"end":26697,"type":0},{"text":"츠","start":26257,"end":26697,"type":0},{"text":"난","start":26298,"end":26697,"type":0},{"text":"테 ","start":26325,"end":26697,"type":0},{"text":"오","start":26391,"end":26697,"type":0},{"text":"도","start":26410,"end":26697,"type":0},{"text":"리 ","start":26428,"end":26697,"type":0},{"text":"토","start":26486,"end":26697,"type":0},{"text":"바","start":26546,"end":26697,"type":0},{"text":"소","start":26593,"end":26697,"type":0},{"text":"오","start":26609,"end":26697,"type":0}]},{"start":26613,"end":27193,"words":[{"text":"나","start":26713,"end":27093,"type":0},{"text":"야","start":26740,"end":27093,"type":0},{"text":"미","start":26769,"end":27093,"type":0},{"text":"가 ","start":26788,"end":27093,"type":0},{"text":"아","start":26838,"end":27093,"type":0},{"text":"세","start":26869,"end":27093,"type":0},{"text":"데 ","start":26897,"end":27093,"type":0},{"text":"나","start":26965,"end":27093,"type":0},{"text":"가","start":26995,"end":27093,"type":0},{"text":"레","start":27028,"end":27093,"type":0},{"text":"테","start":27045,"end":27093,"type":0}]},{"start":26992,"end":27681,"words":[{"text":"키","start":27092,"end":27581,"type":0},{"text":"에","start":27121,"end":27581,"type":0},{"text":"테 ","start":27152,"end":27581,"type":0},{"text":"카","start":27281,"end":27581,"type":0},{"text":"라","start":27298,"end":27581,"type":0},{"text":"다 ","start":27316,"end":27581,"type":0},{"text":"카","start":27348,"end":27581,"type":0},{"text":"루","start":27365,"end":27581,"type":0},{"text":"이 ","start":27382,"end":27581,"type":0},{"text":"미","start":27447,"end":27581,"type":0},{"text":"타","start":27465,"end":27581,"type":0},{"text":"이","start":27481,"end":27581,"type":0},{"text":"사","start":27495,"end":27581,"type":0}]},{"start":27496,"end":28320,"words":[{"text":"타","start":27596,"end":28220,"type":0},{"text":"노","start":27630,"end":28220,"type":0},{"text":"시","start":27661,"end":28220,"type":0},{"text":"이 ","start":27677,"end":28220,"type":0},{"text":"히","start":27700,"end":28220,"type":0},{"text":"와 ","start":27727,"end":28220,"type":0},{"text":"앗","start":27789,"end":28220,"type":0},{"text":"토 ","start":27818,"end":28220,"type":0},{"text":"이","start":27847,"end":28220,"type":0},{"text":"우","start":27864,"end":28220,"type":0},{"text":"마","start":27886,"end":28220,"type":0},{"text":"니 ","start":27914,"end":28220,"type":0},{"text":"오","start":27945,"end":28220,"type":0},{"text":"와","start":27990,"end":28220,"type":0},{"text":"룻","start":28030,"end":28220,"type":0},{"text":"테 ","start":28068,"end":28220,"type":0},{"text":"코","start":28144,"end":28220,"type":0},{"text":"토","start":28160,"end":28220,"type":0},{"text":"오","start":28182,"end":28220,"type":0}]},{"start":28132,"end":28810,"words":[{"text":"이","start":28232,"end":28710,"type":0},{"text":"마","start":28260,"end":28710,"type":0},{"text":"와 ","start":28287,"end":28710,"type":0},{"text":"마","start":28317,"end":28710,"type":0},{"text":"다 ","start":28348,"end":28710,"type":0},{"text":"이","start":28413,"end":28710,"type":0},{"text":"와","start":28435,"end":28710,"type":0},{"text":"나","start":28450,"end":28710,"type":0},{"text":"이","start":28489,"end":28710,"type":0},{"text":"데 ","start":28513,"end":28710,"type":0},{"text":"이","start":28566,"end":28710,"type":0},{"text":"테","start":28614,"end":28710,"type":0}]},{"start":28635,"end":29346,"words":[{"text":"카","start":28735,"end":29246,"type":0},{"text":"에","start":28767,"end":29246,"type":0},{"text":"리","start":28798,"end":29246,"type":0},{"text":"타","start":28816,"end":29246,"type":0},{"text":"쿠","start":28857,"end":29246,"type":0},{"text":"나","start":28891,"end":29246,"type":0},{"text":"이 ","start":28923,"end":29246,"type":0},{"text":"카","start":28987,"end":29246,"type":0},{"text":"에","start":29016,"end":29246,"type":0},{"text":"라","start":29049,"end":29246,"type":0},{"text":"나","start":29067,"end":29246,"type":0},{"text":"이","start":29082,"end":29246,"type":0},{"text":"데 ","start":29114,"end":29246,"type":0},{"text":"이","start":29147,"end":29246,"type":0},{"text":"이","start":29163,"end":29246,"type":0},{"text":"요","start":29179,"end":29246,"type":0}]},{"start":29145,"end":30169,"words":[{"text":"유","start":29245,"end":30069,"type":0},{"text":"메","start":29270,"end":30069,"type":0},{"text":"노 ","start":29296,"end":30069,"type":0},{"text":"요","start":29315,"end":30069,"type":0},{"text":"오","start":29330,"end":30069,"type":0},{"text":"나 ","start":29375,"end":30069,"type":0},{"text":"슌","start":29552,"end":30069,"type":0},{"text":"칸","start":29587,"end":30069,"type":0},{"text":"가 ","start":29643,"end":30069,"type":0},{"text":"코","start":29679,"end":30069,"type":0},{"text":"코","start":29704,"end":30069,"type":0},{"text":"니 ","start":29720,"end":30069,"type":0},{"text":"아","start":29768,"end":30069,"type":0},{"text":"루","start":29808,"end":30069,"type":0},{"text":"요","start":29827,"end":30069,"type":0}]},{"start":0,"end":100,"words":[{"text":"","start":0,"end":0,"type":0}]},{"start":30080,"end":30575,"words":[{"text":"Po- ","start":30180,"end":30314,"type":0},{"text":"Po- ","start":30192,"end":30314,"type":0},{"text":"Pop! ","start":30219,"end":30314,"type":0},{"text":"맛","start":30221,"end":30475,"type":0},{"text":"테","start":30240,"end":30475,"type":0},{"text":"탄","start":30254,"end":30475,"type":0},{"text":"다 ","start":30270,"end":30475,"type":0},{"text":"맛","start":30285,"end":30475,"type":0},{"text":"테","start":30300,"end":30475,"type":0},{"text":"탄","start":30316,"end":30475,"type":0},{"text":"다 ","start":30331,"end":30475,"type":0},{"text":"키","start":30351,"end":30475,"type":0},{"text":"미","start":30377,"end":30475,"type":0},{"text":"오","start":30396,"end":30475,"type":0}]},{"start":30329,"end":30819,"words":[{"text":"Po- ","start":30429,"end":30553,"type":0},{"text":"Po- ","start":30443,"end":30553,"type":0},{"text":"Pop! ","start":30473,"end":30553,"type":0},{"text":"쿄","start":30470,"end":30719,"type":0},{"text":"오","start":30485,"end":30719,"type":0},{"text":"와 ","start":30501,"end":30719,"type":0},{"text":"즛","start":30516,"end":30719,"type":0},{"text":"토 ","start":30532,"end":30719,"type":0},{"text":"하","start":30560,"end":30719,"type":0},{"text":"나","start":30574,"end":30719,"type":0},{"text":"사","start":30593,"end":30719,"type":0},{"text":"나","start":30608,"end":30719,"type":0},{"text":"이","start":30633,"end":30719,"type":0},{"text":"요","start":30649,"end":30719,"type":0}]},{"start":30580,"end":31098,"words":[{"text":"Po- ","start":30680,"end":30822,"type":0},{"text":"Po- ","start":30695,"end":30822,"type":0},{"text":"Pop! ","start":30724,"end":30822,"type":0},{"text":"Pop","start":30725,"end":30998,"type":0},{"text":"ping ","start":30755,"end":30998,"type":0},{"text":"Par","start":30785,"end":30998,"type":0},{"text":"ty ","start":30815,"end":30998,"type":0},{"text":"Eve","start":30847,"end":30998,"type":0},{"text":"ry","start":30879,"end":30998,"type":0},{"text":"bo","start":30896,"end":30998,"type":0},{"text":"dy ","start":30912,"end":30998,"type":0},{"text":"dan","start":30942,"end":30998,"type":0},{"text":"ce!","start":30957,"end":30998,"type":0}]},{"start":30902,"end":31456,"words":[{"text":"Yeah!","start":31002,"end":31356,"type":3}]}]}